jelastic_client/__init__.py
jelastic_client/account_client.py
jelastic_client/control_client.py
jelastic_client/core/__init__.py
jelastic_client/core/api_client.py
jelastic_client/core/base_client.py
jelastic_client/core/exceptions.py
jelastic_client/env_info.py
jelastic_client/env_settings.py
jelastic_client/env_status.py
jelastic_client/factory.py
jelastic_client/file_client.py
jelastic_client/jps_client.py
jelastic_client/node.py
jelastic_client/node_settings.py
jelastic_client/user_info.py
jelastic_client-8.1.1.1.dist-info/WHEEL
jelastic_client-8.1.1.1.dist-info/METADATA
jelastic_client-8.1.1.1.dist-info/RECORD
