Metadata-Version: 2.1
Name: jelastic-client
Version: 8.1.1.1
Summary: A client library for Jelastic
Home-page: https://github.com/softozor/jelastic-client
License: MIT
Author: softozor
Author-email: softozor@gmail.com
Requires-Python: >=3.8,<4.0
Classifier: License :: OSI Approved :: MIT License
Classifier: Programming Language :: Python :: 3
Classifier: Programming Language :: Python :: 3.8
Classifier: Programming Language :: Python :: 3.9
Classifier: Programming Language :: Python :: 3.10
Classifier: Programming Language :: Python :: 3.11
Requires-Dist: dataclasses-json (==0.5.7)
Requires-Dist: httpx[http2] (>=0.18)
Requires-Dist: pyyaml (>=6.0,<7.0)
Requires-Dist: requests (==2.28.1)
Requires-Dist: types-pyyaml (>=6.0.12.4,<7.0.0.0)
Project-URL: Repository, https://github.com/softozor/jelastic-client
